[{"BC_DOC":"2.7","BC_NO":null,"SLIP_DATE":"14-OCT-19","SLIP_NO":"SJU.A.0305","CUSTOMER":"ASTOM INDONESIA, PT","CURR_MARK":"US$","SLIP_AMOUNT":"1836","AMT":"US$ 1,836.00000"},{"BC_DOC":"3.0","BC_NO":"3.0","SLIP_DATE":"02-FEB-18","SLIP_NO":"01\/RE-EXPORT\/18","CUSTOMER":"OHGITANI (S) PTE, LTD","CURR_MARK":"US$","SLIP_AMOUNT":"11417.13","AMT":"US$ 11,417.13000"},{"BC_DOC":"4.1","BC_NO":null,"SLIP_DATE":"13-MAY-19","SLIP_NO":"SJU.A.0296","CUSTOMER":"SINAR  KARYA  NUSA, CV","CURR_MARK":"US$","SLIP_AMOUNT":"896.564885","AMT":"US$ 896.56489"}]